<?xml version="1.0" encoding="utf-8"?>   
<skills>
<jineng>
<name>属性加强(G)</name>
<shuoming>永久性的提昇灵活、智慧和力量。</shuoming>
<jineng_1>(第1级)-所有状态增加2点。</jineng_1>
<jineng_2>(第2级)-所有状态增加2点。</jineng_2>
<jineng_3>(第3级)-所有状态增加2点。</jineng_3>
<jineng_4>(第4级)-所有状态增加2点。</jineng_4>
</jineng>
<jineng>
<name>炸药桶(E)</name>
<shuoming>在地上埋藏一个炸药桶，当敌人经过时将会引爆，造成伤害。场上最多只能放置16个。</shuoming>
<jineng_1>(第1级)-造成200点伤害。</jineng_1>
<jineng_2>(第2级)-造成250点伤害。</jineng_2>
<jineng_3>(第3级)-造成350点伤害。</jineng_3>
<jineng_4>(第4级)-造成450点伤害。</jineng_4>
</jineng>
<jineng>
<name>炸弹投掷（R）</name>
<shuoming>用炸弹投掷一块区域，并击晕敌方部队 1.01 秒，以及对附近敌方部队造成伤害。</shuoming>
<jineng_1>(第1级)-50点的伤害。</jineng_1>
<jineng_2>(第2级)-75点的伤害。</jineng_2>
<jineng_3>(第3级)-100点的伤害。</jineng_3>
<jineng_4>(第4级)-125点的伤害。</jineng_4>
</jineng>
<jineng>
<name>同归於尽(T)</name>
<shuoming>当死亡时，引爆身上所有炸药与敌人同归於尽。爆炸范围500。</shuoming>
<jineng_1>(第1级)-造成周围敌方350点伤害(最大)。</jineng_1>
<jineng_2>(第2级)-造成周围敌方450点伤害(最大)。</jineng_2>
<jineng_3>(第3级)-造成周围敌方650点伤害(最大)。</jineng_3>
<jineng_4>(第4级)-造成周围敌方850点伤害(最大)。</jineng_4>
</jineng>
<jineng>
<name>引线地雷(W)</name>
<shuoming>在地上埋藏一个附有引线的炸药桶，可以在适当的时机引爆。持续180秒。</shuoming>
<jineng_1>(第1级)-造成300点范围伤害。</jineng_1>
<jineng_2>(第2级)-造成400点范围伤害。</jineng_2>
<jineng_3>(第3级)-造成500点范围伤害。</jineng_3>
</jineng>
</skills>